{"otherData": {},"traceEvents":[{"cat":"function","dur":3,"name":"__cdecl Hazel::OpenGLTexture2D::~OpenGLTexture2D(void)","ph":"X","pid":0,"tid":213855159,"ts":977725179873},{"cat":"function","dur":1,"name":"__cdecl Hazel::OpenGLShader::~OpenGLShader(void)","ph":"X","pid":0,"tid":213855159,"ts":977725179900},{"cat":"function","dur":1,"name":"__cdecl Hazel::OpenGLIndexBuffer::~OpenGLIndexBuffer(void)","ph":"X","pid":0,"tid":213855159,"ts":977725179914},{"cat":"function","dur":0,"name":"__cdecl Hazel::OpenGLVertexBuffer::~OpenGLVertexBuffer(void)","ph":"X","pid":0,"tid":213855159,"ts":977725179928},{"cat":"function","dur":68,"name":"void __cdecl Hazel::Renderer2D::Shutdown(void)","ph":"X","pid":0,"tid":213855159,"ts":977725179872},{"cat":"function","dur":79,"name":"__cdecl Hazel::Application::~Application(void)","ph":"X","pid":0,"tid":213855159,"ts":977725179872},{"cat":"function","dur":0,"name":"__cdecl Hazel::OpenGLTexture2D::~OpenGLTexture2D(void)","ph":"X","pid":0,"tid":213855159,"ts":977725179964},{"cat":"function","dur":30458,"name":"void __cdecl Hazel::WindowsWindow::Shutdown(void)","ph":"X","pid":0,"tid":213855159,"ts":977725179976},{"cat":"function","dur":30493,"name":"__cdecl Hazel::WindowsWindow::~WindowsWindow(void)","ph":"X","pid":0,"tid":213855159,"ts":977725179976}]}